<SliderGroups>
    <Group name="CBBE">
        <Member name="Eli Armoured Jumpsuit"/>
        <Member name="Eli Armoured Vault Jumpsuit"/>
        <Member name="Eli BackPack"/>
        <Member name="Eli Bandolier"/>
        <Member name="Eli Cait&apos;s Outfit"/>
        <Member name="Eli Courier Duster"/>
        <Member name="Eli Courier Duster Bag"/>
        <Member name="Eli Curie&apos;s Outfit"/>
        <Member name="Eli Danse&apos;s Outfit"/>
        <Member name="Eli Danse&apos;s Outfit No Jacket"/>
        <Member name="Eli Deacon Outfit"/>
        <Member name="Eli Deacon&apos;s Outfit 2"/>
        <Member name="Eli Field Medic Outfit"/>
        <Member name="Eli Flannels Tee and Jumpsuit"/>
        <Member name="Eli Grognak Top and Camos"/>
        <Member name="Eli Institute Casual Outfit"/>
        <Member name="Eli Institute Course Uniform"/>
        <Member name="Eli Institute Director&apos;s Armoured Uniform"/>
        <Member name="Eli Institute Director&apos;s Uniform"/>
        <Member name="Eli MacCready&apos;s Outfit"/>
        <Member name="Eli Outfit Comic Fan"/>
        <Member name="Eli Piper&apos;s Outfit"/>
        <Member name="Eli Preston&apos;s Outfit"/>
        <Member name="Eli Raider Heavy Armour"/>
        <Member name="Eli Raider Skimpy Armour"/>
        <Member name="Eli Railroad Fatigues"/>
        <Member name="Eli Red Ranger Outfit"/>
        <Member name="Eli Road Fatigues"/>
        <Member name="Eli Road Flannels"/>
        <Member name="Eli Road Fury"/>
        <Member name="Eli Rugged Flannels"/>
        <Member name="Eli Shorts Outfit"/>
        <Member name="Eli Sleeves Tee and Fatigues"/>
        <Member name="Eli T-Shirt Fatigues"/>
        <Member name="Eli T-Shirt Fatigues and Vest"/>
        <Member name="Eli T-Shirt with Long Sleeves"/>
        <Member name="Eli Tunnel Snakes Outfit"/>
        <Member name="Eli Tunnel Snakes Shirt and Vault Suit"/>
        <Member name="Eli Unarmoured Jumpsuit"/>
        <Member name="Eli Urban Jumpsuit Tee"/>
        <Member name="Eli Urban Ranger Outfit"/>
        <Member name="Eli Urban Ranger Outfit with Bags"/>
        <Member name="Eli Vault Dweller Wastelander Armour"/>
        <Member name="Eli Vault Raider Outfit"/>
        <Member name="Eli Vault Scientist Jumpsuit"/>
        <Member name="Eli Wasteland Doctor"/>
        <Member name="Eli Wasteland Hipster"/>
        <Member name="Eli Wasteland Militia"/>
        <Member name="Eli Winter Vest and Tee"/>
        <Member name="Eli X6&apos;s Outfit"/>
        <Member name="Eli Messenger Bag"/>
    </Group>
    <Group name="Eli Armour Compendium">
        <Member name="Eli Armoured Jumpsuit"/>
        <Member name="Eli Armoured Vault Jumpsuit"/>
        <Member name="Eli BackPack"/>
        <Member name="Eli Bandolier"/>
        <Member name="Eli Cait&apos;s Outfit"/>
        <Member name="Eli Courier Duster"/>
        <Member name="Eli Courier Duster Bag"/>
        <Member name="Eli Curie&apos;s Outfit"/>
        <Member name="Eli Danse&apos;s Outfit"/>
        <Member name="Eli Danse&apos;s Outfit No Jacket"/>
        <Member name="Eli Deacon Outfit"/>
        <Member name="Eli Deacon&apos;s Outfit 2"/>
        <Member name="Eli Field Medic Outfit"/>
        <Member name="Eli Flannels Tee and Jumpsuit"/>
        <Member name="Eli Grognak Top and Camos"/>
        <Member name="Eli Institute Casual Outfit"/>
        <Member name="Eli Institute Course Uniform"/>
        <Member name="Eli Institute Director&apos;s Armoured Uniform"/>
        <Member name="Eli Institute Director&apos;s Uniform"/>
        <Member name="Eli MacCready&apos;s Outfit"/>
        <Member name="Eli Outfit Comic Fan"/>
        <Member name="Eli Piper&apos;s Outfit"/>
        <Member name="Eli Preston&apos;s Outfit"/>
        <Member name="Eli Raider Heavy Armour"/>
        <Member name="Eli Raider Skimpy Armour"/>
        <Member name="Eli Railroad Fatigues"/>
        <Member name="Eli Red Ranger Outfit"/>
        <Member name="Eli Road Fatigues"/>
        <Member name="Eli Road Flannels"/>
        <Member name="Eli Road Fury"/>
        <Member name="Eli Rugged Flannels"/>
        <Member name="Eli Shorts Outfit"/>
        <Member name="Eli Sleeves Tee and Fatigues"/>
        <Member name="Eli T-Shirt Fatigues"/>
        <Member name="Eli T-Shirt Fatigues and Vest"/>
        <Member name="Eli T-Shirt with Long Sleeves"/>
        <Member name="Eli Tunnel Snakes Outfit"/>
        <Member name="Eli Tunnel Snakes Shirt and Vault Suit"/>
        <Member name="Eli Unarmoured Jumpsuit"/>
        <Member name="Eli Urban Jumpsuit Tee"/>
        <Member name="Eli Urban Ranger Outfit"/>
        <Member name="Eli Urban Ranger Outfit with Bags"/>
        <Member name="Eli Vault Dweller Wastelander Armour"/>
        <Member name="Eli Vault Raider Outfit"/>
        <Member name="Eli Vault Scientist Jumpsuit"/>
        <Member name="Eli Wasteland Doctor"/>
        <Member name="Eli Wasteland Hipster"/>
        <Member name="Eli Wasteland Militia"/>
        <Member name="Eli Winter Vest and Tee"/>
        <Member name="Eli X6&apos;s Outfit"/>
        <Member name="Eli Messenger Bag"/>
    </Group>
</SliderGroups>
